elasticsearch_logging_handler/__init__.py
elasticsearch_logging_handler/_handlers.py
elasticsearch_logging_handler/_queue_handler.py
elasticsearch_logging_handler/_sending_handler.py
elasticsearch_logging_handler-1.0.1.dist-info/LICENSE
elasticsearch_logging_handler-1.0.1.dist-info/METADATA
elasticsearch_logging_handler-1.0.1.dist-info/WHEEL
elasticsearch_logging_handler-1.0.1.dist-info/top_level.txt
elasticsearch_logging_handler-1.0.1.dist-info/RECORD
