Metadata-Version: 2.1
Name: elasticsearch-logging-handler
Version: 1.0.1
Summary: Minimalistic Elasticsearch logging handler
Home-page: https://github.com/Mulanir/python-elasticsearch-logging
Author: Bohdan Sydorov
Author-email: bodiasyd@gmail.com
Classifier: Development Status :: 4 - Beta
Classifier: Programming Language :: Python :: 3.7
Classifier: License :: OSI Approved :: MIT License
Classifier: Topic :: System :: Logging
Requires-Python: >=3.7
License-File: LICENSE
Requires-Dist: elasticsearch (<8.0.0)
Requires-Dist: pytz
